braid/__init__.py
braid/critic.py
braid/engine.py
braid/generator.py
braid/masking.py
braid/metrics.py
braid/module.py
braid/optimizer.py
braid/parser.py
braid/signatures.py
braid/training.py
braid/utils.py
braid/validators.py
braid_dspy-0.2.3.dist-info/licenses/AUTHORS.md
braid_dspy-0.2.3.dist-info/licenses/LICENSE
braid_dspy-0.2.3.dist-info/METADATA
braid_dspy-0.2.3.dist-info/WHEEL
braid_dspy-0.2.3.dist-info/top_level.txt
braid_dspy-0.2.3.dist-info/RECORD
