Metadata-Version: 2.4
Name: braid-dspy
Version: 0.2.3
Summary: BRAID (Bounded Reasoning for Autonomous Inference and Decisions) integration for DSPy framework
Home-page: https://github.com/ziyacivan/braid-dspy
Author: Braid-DSPy Contributors
License: MIT
Project-URL: Homepage, https://github.com/ziyacivan/braid-dspy
Project-URL: Documentation, https://braid-dspy.readthedocs.io/en/stable/
Project-URL: Repository, https://github.com/ziyacivan/braid-dspy
Project-URL: Issues, https://github.com/ziyacivan/braid-dspy/issues
Keywords: dspy,braid,reasoning,llm,ai,mermaid,grd
Classifier: Development Status :: 3 - Alpha
Classifier: Intended Audience :: Developers
Classifier: Intended Audience :: Science/Research
Classifier: License :: OSI Approved :: MIT License
Classifier: Programming Language :: Python :: 3
Classifier: Programming Language :: Python :: 3.9
Classifier: Programming Language :: Python :: 3.10
Classifier: Programming Language :: Python :: 3.11
Classifier: Topic :: Scientific/Engineering :: Artificial Intelligence
Requires-Python: >=3.9
License-File: LICENSE
License-File: AUTHORS.md
Requires-Dist: dspy-ai>=2.0.0
Provides-Extra: dev
Requires-Dist: pytest>=7.0.0; extra == "dev"
Requires-Dist: pytest-cov>=4.0.0; extra == "dev"
Requires-Dist: black>=23.0.0; extra == "dev"
Requires-Dist: pre-commit>=3.0.0; extra == "dev"
Requires-Dist: isort>=5.13.0; extra == "dev"
Provides-Extra: docs
Requires-Dist: sphinx>=6.0.0; extra == "docs"
Requires-Dist: sphinx-rtd-theme>=1.3.0; extra == "docs"
Requires-Dist: myst-parser>=2.0.0; extra == "docs"
Requires-Dist: sphinx-copybutton>=0.5.0; extra == "docs"
Dynamic: home-page
Dynamic: license-file
Dynamic: requires-python
